stellars_jupyterlab_favourites/__init__.py
stellars_jupyterlab_favourites-1.0.3.dist-info/METADATA
stellars_jupyterlab_favourites-1.0.3.dist-info/WHEEL
stellars_jupyterlab_favourites-1.0.3.dist-info/RECORD
