Metadata-Version: 2.4
Name: stellars_jupyterlab_favourites
Version: 1.0.3
Summary: Metapackage aggregating Stellars JupyterLab extensions, fixes, themes, and favourite third-party packages
Project-URL: Homepage, https://github.com/stellarshenson/stellars_jupyterlab_favourites
Project-URL: Repository, https://github.com/stellarshenson/stellars_jupyterlab_favourites
Author-email: Konrad Jelen <konrad.jelen+github@gmail.com>
License: MIT
Keywords: extensions,jupyter,jupyterlab,themes
Classifier: Framework :: Jupyter
Classifier: Framework :: Jupyter :: JupyterLab
Classifier: Framework :: Jupyter :: JupyterLab :: 4
Classifier: License :: OSI Approved :: MIT License
Classifier: Programming Language :: Python
Classifier: Programming Language :: Python :: 3
Classifier: Programming Language :: Python :: 3.10
Classifier: Programming Language :: Python :: 3.11
Classifier: Programming Language :: Python :: 3.12
Requires-Python: >=3.10
Requires-Dist: jupyter-app-launcher
Requires-Dist: jupyter-resource-usage
Requires-Dist: jupyterlab-code-formatter
Requires-Dist: jupyterlab-execute-time
Requires-Dist: jupyterlab-favorites
Requires-Dist: jupyterlab-git
Requires-Dist: jupyterlab-iframe
Requires-Dist: jupyterlab-stellars-darcula-theme
Requires-Dist: jupyterlab-stellars-sublime-theme
Requires-Dist: jupytext
Requires-Dist: nb-venv-kernels
Requires-Dist: nbdime
Requires-Dist: notebook-intelligence
Requires-Dist: stellars-jupyterlab-extensions
Requires-Dist: stellars-jupyterlab-fixes
